PyRth/__init__.py
PyRth/transient_core.py
PyRth/transient_defaults.py
PyRth/transient_engine.py
PyRth/transient_filter_functions.py
PyRth/transient_mpfr_utils.py
PyRth/transient_optimizer.py
PyRth/transient_scripts.py
PyRth/exporter/__init__.py
PyRth/exporter/transient_base_exporter.py
PyRth/exporter/transient_base_fig.py
PyRth/exporter/transient_csv_exporter.py
PyRth/exporter/transient_figure_exporter.py
PyRth/exporter/transient_figures.py
PyRth/exporter/transient_io_manager.py
PyRth/utils/__init__.py
PyRth/utils/optimizer_utils.py
PyRth/utils/transient_utils.py
pyrth-1.0.2.dist-info/LICENSE.txt
pyrth-1.0.2.dist-info/METADATA
pyrth-1.0.2.dist-info/WHEEL
pyrth-1.0.2.dist-info/top_level.txt
pyrth-1.0.2.dist-info/RECORD
