Metadata-Version: 2.2
Name: PyRth
Version: 1.0.2
Summary: A tool for thermal transient analysis
Author-email: "Nils J. Ziegeler" <ziegeler.nilsjonas@fh-swf.de>
Project-URL: Homepage, https://github.com/nizie002/PyRth
Classifier: Programming Language :: Python :: 3
Classifier: License :: OSI Approved :: MIT License
Classifier: Operating System :: OS Independent
Requires-Python: >=3.11
License-File: LICENSE.txt
Requires-Dist: numpy<2.0.0,>=1.26.4
Requires-Dist: scipy<2.0.0,>=1.14.1
Requires-Dist: matplotlib<4.0.0,>=3.9.3
Requires-Dist: numba<1.0.0,>=0.60.0
Requires-Dist: gmpy2<3.0.0,>=2.2.1
